TemDataBrowser/__init__.py
TemDataBrowser/images/TemDataBrowser_window.png
TemDataBrowser-1.0.6.dist-info/METADATA
TemDataBrowser-1.0.6.dist-info/WHEEL
TemDataBrowser-1.0.6.dist-info/entry_points.txt
TemDataBrowser-1.0.6.dist-info/top_level.txt
TemDataBrowser-1.0.6.dist-info/RECORD
