Metadata-Version: 2.1
Name: TemDataBrowser
Version: 1.0.6
Summary: Graphical user interface to view transmission electron microscopy data.
Author-email: Peter Ercius <percius@lbl.gov>
Requires-Python: >=3.8
Requires-Dist: numpy
Requires-Dist: pyqtgraph
Requires-Dist: ScopeFoundry >=1.5
Requires-Dist: ncempy
Requires-Dist: scipy
Requires-Dist: imageio >2.17
